cpymad_lhc/__init__.py
cpymad_lhc/corrector_limits.py
cpymad_lhc/coupling_correction.py
cpymad_lhc/coupling_knob.py
cpymad_lhc/general.py
cpymad_lhc/io.py
cpymad_lhc/ir_orbit.py
cpymad_lhc/logging.py
cpymad_lhc-0.2.1.dist-info/METADATA
cpymad_lhc-0.2.1.dist-info/WHEEL
cpymad_lhc-0.2.1.dist-info/licenses/LICENSE
cpymad_lhc-0.2.1.dist-info/RECORD
